pyeboot/sign.cpython-311-darwin.so
pyeboot/__init__.py
pyeboot/decrypt.cpython-311-darwin.so
pyeboot-0.2.2.dist-info/RECORD
pyeboot-0.2.2.dist-info/LICENSE
pyeboot-0.2.2.dist-info/WHEEL
pyeboot-0.2.2.dist-info/top_level.txt
pyeboot-0.2.2.dist-info/METADATA
